asdkiller123/__init__.py
asdkiller123-0.1.0.dist-info/METADATA
asdkiller123-0.1.0.dist-info/WHEEL
asdkiller123-0.1.0.dist-info/top_level.txt
asdkiller123-0.1.0.dist-info/RECORD
