Metadata-Version: 2.4
Name: asdkiller123
Version: 0.1.0
Summary: Egy próba modul
Author: A neved
Dynamic: author
Dynamic: summary
